[
  {
    "title": "Nos Russian Hgs",
    "url": "https://comblocmarket.com/classifieds1/nos-russian-hgs.6904/",
    "price": "",
    "date": "2025-06-04T23:08:32-0400"
  },
  {
    "title": "CZ-75B",
    "url": "https://comblocmarket.com/classifieds1/cz-75b.5102/",
    "price": "",
    "date": "2025-01-01T19:57:14-0500"
  },
  {
    "title": "Brand new Alg akt UL",
    "url": "https://comblocmarket.com/classifieds1/brand-new-alg-akt-ul.6903/",
    "price": "",
    "date": "2025-06-04T22:32:02-0400"
  },
  {
    "title": "Egyptian Maadi AKM Parts Kit - Arabic Markings",
    "url": "https://comblocmarket.com/classifieds1/egyptian-maadi-akm-parts-kit-arabic-markings.6394/",
    "price": "",
    "date": "2025-04-22T18:11:47-0400"
  },
  {
    "title": "JMAC Customs AK Parts",
    "url": "https://comblocmarket.com/classifieds1/jmac-customs-ak-parts.6732/",
    "price": "",
    "date": "2025-05-22T21:52:28-0400"
  },
  {
    "title": "Suppressor HUB direct thread adapters, DA Wolverine thread inserts w/collars",
    "url": "https://comblocmarket.com/classifieds1/suppressor-hub-direct-thread-adapters-da-wolverine-thread-inserts-w-collars.6123/",
    "price": "",
    "date": "2025-04-02T17:33:33-0400"
  },
  {
    "title": "Arsenal Saiga 12 rail/handguard set",
    "url": "https://comblocmarket.com/classifieds1/arsenal-saiga-12-rail-handguard-set.6774/",
    "price": "",
    "date": "2025-05-25T13:10:20-0400"
  },
  {
    "title": "Podgornov’s Kalashnikov assault rifles and light machine guns hard copy",
    "url": "https://comblocmarket.com/classifieds1/podgornov%E2%80%99s-kalashnikov-assault-rifles-and-light-machine-guns-hard-copy.5334/",
    "price": "",
    "date": "2025-01-25T16:47:48-0500"
  },
  {
    "title": "AKSu Krink sling $36, AK-12 Sling $300, AK sling $25, RPK Pad $16, RPK sling w/ pad $40. SVD cheek pad $...",
    "url": "https://comblocmarket.com/classifieds1/aksu-krink-sling-36-ak-12-sling-300-ak-sling-25-rpk-pad-16-rpk-sling-w-pad-40-svd-cheek-pad-110-4-flat-shipping-ca.269/",
    "price": "$36",
    "date": "2023-07-20T18:29:14-0400"
  },
  {
    "title": "[Price Drop] FB Radom Polish Beryl Folding Stock Retro",
    "url": "https://comblocmarket.com/classifieds1/price-drop-fb-radom-polish-beryl-folding-stock-retro.6306/",
    "price": "",
    "date": "2025-04-15T11:43:09-0400"
  },
  {
    "title": "Bulgarian AK-74 Gas Block",
    "url": "https://comblocmarket.com/classifieds1/bulgarian-ak-74-gas-block.6902/",
    "price": "",
    "date": "2025-06-04T19:22:09-0400"
  },
  {
    "title": "South African R4/ R5/ R6 Front Sight Hood with Night Sight",
    "url": "https://comblocmarket.com/classifieds1/south-african-r4-r5-r6-front-sight-hood-with-night-sight.6901/",
    "price": "",
    "date": "2025-06-04T19:17:23-0400"
  },
  {
    "title": "South African R4/ R5/ R6 Front Sight Hood",
    "url": "https://comblocmarket.com/classifieds1/south-african-r4-r5-r6-front-sight-hood.6900/",
    "price": "",
    "date": "2025-06-04T19:08:51-0400"
  },
  {
    "title": "2 Izzy BAKELITES (5.45)",
    "url": "https://comblocmarket.com/classifieds1/2-izzy-bakelites-5-45.4346/",
    "price": "",
    "date": "2024-10-12T16:04:44-0400"
  },
  {
    "title": "Russian Izhmash AK-105 SBR, Bulgarian Arsenal SLR-107CR SBR, Izhmash Saiga-12 11\" SBS or parts kits",
    "url": "https://comblocmarket.com/classifieds1/russian-izhmash-ak-105-sbr-bulgarian-arsenal-slr-107cr-sbr-izhmash-saiga-12-11-sbs-or-parts-kits.6843/",
    "price": "",
    "date": "2025-05-31T08:02:52-0400"
  },
  {
    "title": "KNS Precision 1913 Picatinny Stock Adapter for Gen 1 Galil Ace All Calibers $35",
    "url": "https://comblocmarket.com/classifieds1/kns-precision-1913-picatinny-stock-adapter-for-gen-1-galil-ace-all-calibers-35.6755/",
    "price": "$35",
    "date": "2025-05-23T22:57:09-0400"
  },
  {
    "title": "Colt Mk18 mod 0 & Colt 9mm SMG upper, Holosun HE530C red dot, Ruger TD barrels, 14\" Mossberg bbl kits, B...",
    "url": "https://comblocmarket.com/classifieds1/colt-mk18-mod-0-colt-9mm-smg-upper-holosun-he530c-red-dot-ruger-td-barrels-14-mossberg-bbl-kits-benelli-barrel-parts.4742/",
    "price": "",
    "date": "2024-11-22T20:44:23-0500"
  },
  {
    "title": "CZ805 Bren extractors",
    "url": "https://comblocmarket.com/classifieds1/cz805-bren-extractors.5483/",
    "price": "",
    "date": "2025-02-05T14:58:53-0500"
  },
  {
    "title": "AMP-69 handguard",
    "url": "https://comblocmarket.com/classifieds1/amp-69-handguard.6717/",
    "price": "",
    "date": "2025-05-21T06:30:42-0400"
  },
  {
    "title": "Circle ((10)) Bayonet 127B Bulgarian 6x5 in Black",
    "url": "https://comblocmarket.com/classifieds1/circle-10-bayonet-127b-bulgarian-6x5-in-black.6899/",
    "price": "",
    "date": "2025-06-04T16:21:14-0400"
  },
  {
    "title": "Chinese Norinco 56S / Mak90/ Polytech chu wood buttstocks + blems",
    "url": "https://comblocmarket.com/classifieds1/chinese-norinco-56s-mak90-polytech-chu-wood-buttstocks-blems.6847/",
    "price": "",
    "date": "2025-05-31T12:17:08-0400"
  },
  {
    "title": "Bundle of 4 Chinese Flatback mags",
    "url": "https://comblocmarket.com/classifieds1/bundle-of-4-chinese-flatback-mags.6898/",
    "price": "",
    "date": "2025-06-04T16:06:02-0400"
  },
  {
    "title": "7.62x54r lot",
    "url": "https://comblocmarket.com/classifieds1/7-62x54r-lot.6887/",
    "price": "",
    "date": "2025-06-03T13:00:08-0400"
  },
  {
    "title": "WTB Beryl Weaver Optics Rail",
    "url": "https://comblocmarket.com/classifieds1/wtb-beryl-weaver-optics-rail.6897/",
    "price": "",
    "date": "2025-06-04T15:13:55-0400"
  },
  {
    "title": "WTB PSL Gas Tube",
    "url": "https://comblocmarket.com/classifieds1/wtb-psl-gas-tube.6896/",
    "price": "",
    "date": "2025-06-04T14:30:53-0400"
  },
  {
    "title": "Unissued NOS Russian RPK-S 74/RPK-S furniture set",
    "url": "https://comblocmarket.com/classifieds1/unissued-nos-russian-rpk-s-74-rpk-s-furniture-set.6560/",
    "price": "",
    "date": "2025-05-07T22:13:18-0400"
  },
  {
    "title": "izhmash marked russian ak100 stock with russian recoil pad",
    "url": "https://comblocmarket.com/classifieds1/izhmash-marked-russian-ak100-stock-with-russian-recoil-pad.6895/",
    "price": "",
    "date": "2025-06-04T12:35:17-0400"
  },
  {
    "title": "PSA AKM railed dust cover",
    "url": "https://comblocmarket.com/classifieds1/psa-akm-railed-dust-cover.6894/",
    "price": "",
    "date": "2025-06-04T12:27:39-0400"
  },
  {
    "title": "Russian: SVD Cheek Pad, Krinkov Boosters, Bulgy FSB AK-100, ARSENAL AK HG’s, DIGITAL 2-Cell Pouch Drop C...",
    "url": "https://comblocmarket.com/classifieds1/russian-svd-cheek-pad-krinkov-boosters-bulgy-fsb-ak-100-arsenal-ak-hg%E2%80%99s-digital-2-cell-pouch-drop-case-circle-10-mags-east-german-grips.5961/",
    "price": "",
    "date": "2025-03-20T16:09:21-0400"
  },
  {
    "title": "ROMY DONG, RUSSIAN KRINK BOOSTERS, Flora CASE, 1000M 800M Rear Leafs, Bulgy AK Bakelite HG Set, Mak Mag,...",
    "url": "https://comblocmarket.com/classifieds1/romy-dong-russian-krink-boosters-flora-case-1000m-800m-rear-leafs-bulgy-ak-bakelite-hg-set-mak-mag-vepr-folding-stock-russian-trunnion.5182/",
    "price": "",
    "date": "2025-01-11T13:12:00-0500"
  },
  {
    "title": "Russian: VEPR STOCK, RPK 1000M Sight Leaf, AK100 FSB, Chinese Railed Cover, Gas Tube, MAADI Gas Tube, Ro...",
    "url": "https://comblocmarket.com/classifieds1/russian-vepr-stock-rpk-1000m-sight-leaf-ak100-fsb-chinese-railed-cover-gas-tube-maadi-gas-tube-romy-blue-navy-rpk-aksu-sharkfin-dong.5314/",
    "price": "",
    "date": "2025-01-23T13:18:45-0500"
  },
  {
    "title": "Mint Polytech mags",
    "url": "https://comblocmarket.com/classifieds1/mint-polytech-mags.6307/",
    "price": "",
    "date": "2025-04-15T12:15:51-0400"
  },
  {
    "title": "Arsenal Picatinny Precision Quad Rail",
    "url": "https://comblocmarket.com/classifieds1/arsenal-picatinny-precision-quad-rail.4653/",
    "price": "",
    "date": "2024-11-12T11:50:05-0500"
  },
  {
    "title": "Barwarus ODG BW-T4 and BW-T33 full kit and hardware",
    "url": "https://comblocmarket.com/classifieds1/barwarus-odg-bw-t4-and-bw-t33-full-kit-and-hardware.6698/",
    "price": "",
    "date": "2025-05-19T10:51:48-0400"
  },
  {
    "title": "WTB GP-25 recoil pad with the leather strap",
    "url": "https://comblocmarket.com/classifieds1/wtb-gp-25-recoil-pad-with-the-leather-strap.6893/",
    "price": "",
    "date": "2025-06-04T07:39:28-0400"
  },
  {
    "title": "Russian Akademia Shturm/Storm Muzzle Brakes (prices lowered; 1 left)",
    "url": "https://comblocmarket.com/classifieds1/russian-akademia-shturm-storm-muzzle-brakes-prices-lowered-1-left.5638/",
    "price": "",
    "date": "2025-02-18T12:35:23-0500"
  },
  {
    "title": "Valmet M76 dust cover and pistol grip",
    "url": "https://comblocmarket.com/classifieds1/valmet-m76-dust-cover-and-pistol-grip.4186/",
    "price": "",
    "date": "2024-09-24T17:24:34-0400"
  },
  {
    "title": "Price Drop...1400!! Bulgarian Aks-74n -- OG Barrel -- Morrissey Reciever",
    "url": "https://comblocmarket.com/classifieds1/price-drop-1400-bulgarian-aks-74n-og-barrel-morrissey-reciever.6481/",
    "price": "",
    "date": "2025-05-01T00:48:28-0400"
  },
  {
    "title": "Surplus Steel FAL 20 rd metric Mags - Different Conditions and Countries",
    "url": "https://comblocmarket.com/classifieds1/surplus-steel-fal-20-rd-metric-mags-different-conditions-and-countries.6825/",
    "price": "",
    "date": "2025-05-30T03:13:32-0400"
  },
  {
    "title": "WTB Springfield Trapdoor Antique Rifle/Carbine in 45/70 or 50/70",
    "url": "https://comblocmarket.com/classifieds1/wtb-springfield-trapdoor-antique-rifle-carbine-in-45-70-or-50-70.6168/",
    "price": "",
    "date": "2025-04-06T16:06:54-0400"
  },
  {
    "title": "Primary Arms Advanced Micro Red Dot - NV compatible",
    "url": "https://comblocmarket.com/classifieds1/primary-arms-advanced-micro-red-dot-nv-compatible.6857/",
    "price": "",
    "date": "2025-05-31T23:02:44-0400"
  },
  {
    "title": "Egyptian grip and bayonet ($250 for both)",
    "url": "https://comblocmarket.com/classifieds1/egyptian-grip-and-bayonet-250-for-both.6859/",
    "price": "$250",
    "date": "2025-05-31T23:26:41-0400"
  },
  {
    "title": "Bren 2 Haga lower, Bobro optic mounts, B5 Glow furniture",
    "url": "https://comblocmarket.com/classifieds1/bren-2-haga-lower-bobro-optic-mounts-b5-glow-furniture.6820/",
    "price": "",
    "date": "2025-05-29T22:15:13-0400"
  },
  {
    "title": "Just curious what to appraise",
    "url": "https://comblocmarket.com/classifieds1/just-curious-what-to-appraise.6892/",
    "price": "",
    "date": "2025-06-03T19:44:48-0400"
  },
  {
    "title": "Loose junk. AK74 HG’s, Zenitco RK-6 , Chinese Choate furniture",
    "url": "https://comblocmarket.com/classifieds1/loose-junk-ak74-hg%E2%80%99s-zenitco-rk-6-chinese-choate-furniture.1957/",
    "price": "",
    "date": "2024-01-12T17:24:49-0500"
  },
  {
    "title": "Galil Mag Catch Assembly",
    "url": "https://comblocmarket.com/classifieds1/galil-mag-catch-assembly.6421/",
    "price": "",
    "date": "2025-04-25T20:51:22-0400"
  },
  {
    "title": "Tula Akm bayonet",
    "url": "https://comblocmarket.com/classifieds1/tula-akm-bayonet.6891/",
    "price": "",
    "date": "2025-06-03T18:08:45-0400"
  },
  {
    "title": "Plum mag",
    "url": "https://comblocmarket.com/classifieds1/plum-mag.6890/",
    "price": "",
    "date": "2025-06-03T18:05:09-0400"
  },
  {
    "title": "Magnum Research IMI Galil 361, Valmet M71/S",
    "url": "https://comblocmarket.com/classifieds1/magnum-research-imi-galil-361-valmet-m71-s.6872/",
    "price": "",
    "date": "2025-06-01T17:04:33-0400"
  },
  {
    "title": "Mint condition Nos Russian Hgs",
    "url": "https://comblocmarket.com/classifieds1/mint-condition-nos-russian-hgs.6767/",
    "price": "",
    "date": "2025-05-24T16:06:53-0400"
  },
  {
    "title": "M91/30",
    "url": "https://comblocmarket.com/classifieds1/m91-30.6573/",
    "price": "",
    "date": "2025-05-08T19:05:21-0400"
  },
  {
    "title": "Wasr 10/63",
    "url": "https://comblocmarket.com/classifieds1/wasr-10-63.6647/",
    "price": "",
    "date": "2025-05-14T15:58:14-0400"
  },
  {
    "title": "GSG 22lr STG-44",
    "url": "https://comblocmarket.com/classifieds1/gsg-22lr-stg-44.6613/",
    "price": "",
    "date": "2025-05-11T21:11:21-0400"
  },
  {
    "title": "WTS Lantac Drakon muzzle brake",
    "url": "https://comblocmarket.com/classifieds1/wts-lantac-drakon-muzzle-brake.6848/",
    "price": "",
    "date": "2025-05-31T12:24:58-0400"
  },
  {
    "title": "Russian AK Plum Furniture. Has 1/2 on the pistol grip. 6/2 in handguards, there are also a lot of silver...",
    "url": "https://comblocmarket.com/classifieds1/russian-ak-plum-furniture-has-1-2-on-the-pistol-grip-6-2-in-handguards-there-are-also-a-lot-of-silver-marks.6552/",
    "price": "",
    "date": "2025-05-07T18:09:51-0400"
  },
  {
    "title": "Russian Krinkov handguard set",
    "url": "https://comblocmarket.com/classifieds1/russian-krinkov-handguard-set.6532/",
    "price": "",
    "date": "2025-05-05T22:16:24-0400"
  },
  {
    "title": "SAG AK Stock Adapter/Tube",
    "url": "https://comblocmarket.com/classifieds1/sag-ak-stock-adapter-tube.5419/",
    "price": "",
    "date": "2025-02-01T00:07:37-0500"
  },
  {
    "title": "Arsenal 4.5 Stock set, Valmet bayonet",
    "url": "https://comblocmarket.com/classifieds1/arsenal-4-5-stock-set-valmet-bayonet.6889/",
    "price": "",
    "date": "2025-06-03T14:44:59-0400"
  },
  {
    "title": "Valmet, Galil, Mini 14 Magazines",
    "url": "https://comblocmarket.com/classifieds1/valmet-galil-mini-14-magazines.6888/",
    "price": "",
    "date": "2025-06-03T14:32:37-0400"
  },
  {
    "title": "Cloud Defensive Rein 2.0 w/ switch, mlok and picatinny mounts",
    "url": "https://comblocmarket.com/classifieds1/cloud-defensive-rein-2-0-w-switch-mlok-and-picatinny-mounts.6886/",
    "price": "",
    "date": "2025-06-03T12:42:50-0400"
  },
  {
    "title": "Poly mag and chinese bayo",
    "url": "https://comblocmarket.com/classifieds1/poly-mag-and-chinese-bayo.6829/",
    "price": "",
    "date": "2025-05-30T11:45:48-0400"
  },
  {
    "title": "Hungarian HG Set, Bulgy AK Lower, Romy HG Set W/PM-90 Grip, East German Grips, Russian KRINK Cleaning Ro...",
    "url": "https://comblocmarket.com/classifieds1/hungarian-hg-set-bulgy-ak-lower-romy-hg-set-w-pm-90-grip-east-german-grips-russian-krink-cleaning-rods-flora-pouch-romy-uf-stock-akademia-brake.5738/",
    "price": "",
    "date": "2025-03-02T13:01:06-0500"
  },
  {
    "title": "Romy Forged Trunnion, Polish Lower AK HG, CHINESE SPIKER HG’s, Gas Tube, Chrome Barrel W/Gas Block, Hg R...",
    "url": "https://comblocmarket.com/classifieds1/romy-forged-trunnion-polish-lower-ak-hg-chinese-spiker-hg%E2%80%99s-gas-tube-chrome-barrel-w-gas-block-hg-retainer-fsb-rear-sight-base-fsb-w-post.6271/",
    "price": "",
    "date": "2025-04-13T16:16:11-0400"
  },
  {
    "title": "Yugo Grips $4.50, Romy AK Cleaning Rods $6, Tapco G2 Hammers, Russian 1000M Rear Leaf, GYATA-64 Inert MI...",
    "url": "https://comblocmarket.com/classifieds1/yugo-grips-4-50-romy-ak-cleaning-rods-6-tapco-g2-hammers-russian-1000m-rear-leaf-gyata-64-inert-mine-chinese-chu-upper-ak-gas-tubes-drop-case.4774/",
    "price": "$4.50",
    "date": "2024-11-25T13:44:58-0500"
  },
  {
    "title": "Zastava 556 steel mags/ chinese 84s 556 / a tanker",
    "url": "https://comblocmarket.com/classifieds1/zastava-556-steel-mags-chinese-84s-556-a-tanker.6810/",
    "price": "",
    "date": "2025-05-28T15:30:07-0400"
  },
  {
    "title": "Maadi Grip/s",
    "url": "https://comblocmarket.com/classifieds1/maadi-grip-s.6885/",
    "price": "",
    "date": "2025-06-03T11:25:07-0400"
  },
  {
    "title": "Krink non vented hand guards (unfinished Baltic Birch)",
    "url": "https://comblocmarket.com/classifieds1/krink-non-vented-hand-guards-unfinished-baltic-birch.4880/",
    "price": "",
    "date": "2024-12-05T08:58:53-0500"
  },
  {
    "title": "[WTB] AK build tooling ($1234)",
    "url": "https://comblocmarket.com/classifieds1/wtb-ak-build-tooling-1234.6584/",
    "price": "$1234",
    "date": "2025-05-09T18:14:28-0400"
  },
  {
    "title": "For sale NOS Russian AKM gas block",
    "url": "https://comblocmarket.com/classifieds1/for-sale-nos-russian-akm-gas-block.6688/",
    "price": "",
    "date": "2025-05-17T18:12:40-0400"
  },
  {
    "title": "WTS: NIB Zastava ZPAP Z92 AK pistol 7.62x39",
    "url": "https://comblocmarket.com/classifieds1/wts-nib-zastava-zpap-z92-ak-pistol-7-62x39.6547/",
    "price": "",
    "date": "2025-05-07T16:38:29-0400"
  },
  {
    "title": "WTS: New DSA stripped FAL Forged upper reciever",
    "url": "https://comblocmarket.com/classifieds1/wts-new-dsa-stripped-fal-forged-upper-reciever.6549/",
    "price": "",
    "date": "2025-05-07T16:49:42-0400"
  },
  {
    "title": "BCM lightweight middy upper",
    "url": "https://comblocmarket.com/classifieds1/bcm-lightweight-middy-upper.6754/",
    "price": "",
    "date": "2025-05-23T22:04:15-0400"
  },
  {
    "title": "Russian AKM slings single hook",
    "url": "https://comblocmarket.com/classifieds1/russian-akm-slings-single-hook.6263/",
    "price": "",
    "date": "2025-04-12T20:06:57-0400"
  },
  {
    "title": "Russian spine stamp izhmash mags",
    "url": "https://comblocmarket.com/classifieds1/russian-spine-stamp-izhmash-mags.6693/",
    "price": "",
    "date": "2025-05-18T19:56:59-0400"
  },
  {
    "title": "WTS COLT M16A1 Keychains and Magnets [made from demilled A1 pieces] and M16 CORN HOLDERS",
    "url": "https://comblocmarket.com/classifieds1/wts-colt-m16a1-keychains-and-magnets-made-from-demilled-a1-pieces-and-m16-corn-holders.5857/",
    "price": "",
    "date": "2025-03-10T23:11:35-0400"
  },
  {
    "title": "WTS PARTIAL KITS - Sten MkIII, VZ-26, TRENCH ART Yugo M70 AK, and Suomi KP-44 lowers",
    "url": "https://comblocmarket.com/classifieds1/wts-partial-kits-sten-mkiii-vz-26-trench-art-yugo-m70-ak-and-suomi-kp-44-lowers.5856/",
    "price": "",
    "date": "2025-03-10T23:06:14-0400"
  },
  {
    "title": "WTS Russian SVD Dragunov Front Sight Block Military w/ Bayo Lug",
    "url": "https://comblocmarket.com/classifieds1/wts-russian-svd-dragunov-front-sight-block-military-w-bayo-lug.3318/",
    "price": "",
    "date": "2024-06-12T06:56:17-0400"
  },
  {
    "title": "AK12 Kits & Spare Parts (Magazines/ AKSU Accessories) Shipping From EU Friendly Country",
    "url": "https://comblocmarket.com/classifieds1/ak12-kits-spare-parts-magazines-aksu-accessories-shipping-from-eu-friendly-country.6626/",
    "price": "",
    "date": "2025-05-12T22:37:41-0400"
  },
  {
    "title": "Cheap SAM5",
    "url": "https://comblocmarket.com/classifieds1/cheap-sam5.6883/",
    "price": "",
    "date": "2025-06-02T21:51:13-0400"
  },
  {
    "title": "T1 parts needed",
    "url": "https://comblocmarket.com/classifieds1/t1-parts-needed.5526/",
    "price": "",
    "date": "2025-02-09T08:24:27-0500"
  },
  {
    "title": "Chinese 40 round",
    "url": "https://comblocmarket.com/classifieds1/chinese-40-round.6831/",
    "price": "",
    "date": "2025-05-30T13:51:15-0400"
  },
  {
    "title": "A2 Front Sight - \"F\" Marked",
    "url": "https://comblocmarket.com/classifieds1/a2-front-sight-f-marked.6874/",
    "price": "",
    "date": "2025-06-01T17:17:24-0400"
  },
  {
    "title": "Bulgarian BLEM Top Cover",
    "url": "https://comblocmarket.com/classifieds1/bulgarian-blem-top-cover.6871/",
    "price": "",
    "date": "2025-06-01T16:31:44-0400"
  },
  {
    "title": "AK 5.56 Stainless Steel Pistol Barrel - Wylde Chamber",
    "url": "https://comblocmarket.com/classifieds1/ak-5-56-stainless-steel-pistol-barrel-wylde-chamber.6870/",
    "price": "",
    "date": "2025-06-01T16:21:45-0400"
  },
  {
    "title": "Leather Wraps for AK metal stocks - Underfold, Sidefold, Triangle -  -- Spam Can Leather Tags $10 Xtra --",
    "url": "https://comblocmarket.com/classifieds1/leather-wraps-for-ak-metal-stocks-underfold-sidefold-triangle-spam-can-leather-tags-10-xtra.4588/",
    "price": "$10",
    "date": "2024-11-07T11:59:14-0500"
  },
  {
    "title": "Chinese 87S RPK Brakes, Bulgarian AK74 optic rails, Manticore Night Brakes, Saiga Gas Blocks",
    "url": "https://comblocmarket.com/classifieds1/chinese-87s-rpk-brakes-bulgarian-ak74-optic-rails-manticore-night-brakes-saiga-gas-blocks.6566/",
    "price": "",
    "date": "2025-05-08T10:30:39-0400"
  },
  {
    "title": "Silicone AK Top Cover Gaskets AK47 AKM AK74 - Sale Special 3 pack $20 shipped",
    "url": "https://comblocmarket.com/classifieds1/silicone-ak-top-cover-gaskets-ak47-akm-ak74-sale-special-3-pack-20-shipped.2747/",
    "price": "$20",
    "date": "2024-04-10T10:52:43-0400"
  },
  {
    "title": "WTS/WTT Remington 700 ADL 30-06",
    "url": "https://comblocmarket.com/classifieds1/wts-wtt-remington-700-adl-30-06.6371/",
    "price": "",
    "date": "2025-04-20T17:05:09-0400"
  },
  {
    "title": "Plum ak74 mag",
    "url": "https://comblocmarket.com/classifieds1/plum-ak74-mag.6882/",
    "price": "",
    "date": "2025-06-02T17:59:27-0400"
  },
  {
    "title": "WTS BERYL 5.56",
    "url": "https://comblocmarket.com/classifieds1/wts-beryl-5-56.6526/",
    "price": "",
    "date": "2025-05-04T21:30:45-0400"
  },
  {
    "title": "Double stack makarov ij70 18ah",
    "url": "https://comblocmarket.com/classifieds1/double-stack-makarov-ij70-18ah.6800/",
    "price": "",
    "date": "2025-05-27T14:53:35-0400"
  },
  {
    "title": "Krebs 103k SLR-107FR",
    "url": "https://comblocmarket.com/classifieds1/krebs-103k-slr-107fr.6508/",
    "price": "",
    "date": "2025-05-03T16:23:39-0400"
  },
  {
    "title": "Steiner military 8x30r binoculars",
    "url": "https://comblocmarket.com/classifieds1/steiner-military-8x30r-binoculars.6483/",
    "price": "",
    "date": "2025-05-01T10:03:57-0400"
  },
  {
    "title": "Mixed items (FAL handguards, AK drum, SKS mag, Vortex)",
    "url": "https://comblocmarket.com/classifieds1/mixed-items-fal-handguards-ak-drum-sks-mag-vortex.6025/",
    "price": "",
    "date": "2025-03-25T11:35:42-0400"
  },
  {
    "title": "Century built Bulgarian 74 + 7n6 ammo",
    "url": "https://comblocmarket.com/classifieds1/century-built-bulgarian-74-7n6-ammo.6881/",
    "price": "",
    "date": "2025-06-02T13:25:52-0400"
  },
  {
    "title": "Bulgarian Bakelite Lowers, Russian AK Handguards, Bulgy 5.45 Mags Circle 10, Izzy Forged FRONT Trunnion,...",
    "url": "https://comblocmarket.com/classifieds1/bulgarian-bakelite-lowers-russian-ak-handguards-bulgy-5-45-mags-circle-10-izzy-forged-front-trunnion-romy-upper-w-gas-tube-4-5mm-folding-stock.6156/",
    "price": "",
    "date": "2025-04-05T16:12:14-0400"
  },
  {
    "title": "Russian: Krinkov FSB/Gas Block, Shark Fin Lower, RPK 1000M Rear Sights, AK-100 Rear Sight Base, Vented G...",
    "url": "https://comblocmarket.com/classifieds1/russian-krinkov-fsb-gas-block-shark-fin-lower-rpk-1000m-rear-sights-ak-100-rear-sight-base-vented-gas-tubes-romy-uf-stock-rsb.5480/",
    "price": "",
    "date": "2025-02-05T13:06:01-0500"
  },
  {
    "title": "Boyds AK Stock, Bulgy Bakelite LOWER, Romy RPK 4-Cell Pouches, Tapco G2 FCG, Weiger Mag, Romy PM-90 Grip...",
    "url": "https://comblocmarket.com/classifieds1/boyds-ak-stock-bulgy-bakelite-lower-romy-rpk-4-cell-pouches-tapco-g2-fcg-weiger-mag-romy-pm-90-grip-ar-15-carry-handle.4724/",
    "price": "",
    "date": "2024-11-20T13:38:35-0500"
  },
  {
    "title": "BWK 92 5.56 MAK90 CHECK",
    "url": "https://comblocmarket.com/classifieds1/bwk-92-5-56-mak90-check.6880/",
    "price": "",
    "date": "2025-06-02T11:23:54-0400"
  },
  {
    "title": "IZZY 7.62 BAKELITE MAG FLATBACK",
    "url": "https://comblocmarket.com/classifieds1/izzy-7-62-bakelite-mag-flatback.6879/",
    "price": "",
    "date": "2025-06-02T10:55:33-0400"
  },
  {
    "title": "FN A2 receiver",
    "url": "https://comblocmarket.com/classifieds1/fn-a2-receiver.6817/",
    "price": "",
    "date": "2025-05-29T10:09:39-0400"
  },
  {
    "title": "Molot Vepr FM-AK308-22 - Ca /Commie state ok",
    "url": "https://comblocmarket.com/classifieds1/molot-vepr-fm-ak308-22-ca-commie-state-ok.6684/",
    "price": "",
    "date": "2025-05-17T06:12:57-0400"
  },
  {
    "title": "WTS - CZ Bren 805 (CA ban state compliant) price dropped -200",
    "url": "https://comblocmarket.com/classifieds1/wts-cz-bren-805-ca-ban-state-compliant-price-dropped-200.6466/",
    "price": "",
    "date": "2025-04-30T07:14:02-0400"
  },
  {
    "title": "WBP handguards, Romy bake grip",
    "url": "https://comblocmarket.com/classifieds1/wbp-handguards-romy-bake-grip.6802/",
    "price": "",
    "date": "2025-05-27T17:10:59-0400"
  },
  {
    "title": "Izhmash AK-100 parts",
    "url": "https://comblocmarket.com/classifieds1/izhmash-ak-100-parts.6808/",
    "price": "",
    "date": "2025-05-28T03:46:00-0400"
  },
  {
    "title": "Izhmash bakelite grip",
    "url": "https://comblocmarket.com/classifieds1/izhmash-bakelite-grip.6853/",
    "price": "",
    "date": "2025-05-31T20:11:09-0400"
  },
  {
    "title": "NOS Chinese 762 flat back mags",
    "url": "https://comblocmarket.com/classifieds1/nos-chinese-762-flat-back-mags.6490/",
    "price": "",
    "date": "2025-05-01T19:00:21-0400"
  },
  {
    "title": "Polish Tantal",
    "url": "https://comblocmarket.com/classifieds1/polish-tantal.6489/",
    "price": "",
    "date": "2025-05-01T18:52:39-0400"
  },
  {
    "title": "WTB: US PALM / Tango Down SAM7SF pistol grips",
    "url": "https://comblocmarket.com/classifieds1/wtb-us-palm-tango-down-sam7sf-pistol-grips.6878/",
    "price": "",
    "date": "2025-06-01T23:32:14-0400"
  },
  {
    "title": "Texas bastard. 223 saiga to ar controls and mag",
    "url": "https://comblocmarket.com/classifieds1/texas-bastard-223-saiga-to-ar-controls-and-mag.6877/",
    "price": "",
    "date": "2025-06-01T23:08:01-0400"
  },
  {
    "title": "Zastava M70 Walnut Furniture Set",
    "url": "https://comblocmarket.com/classifieds1/zastava-m70-walnut-furniture-set.6876/",
    "price": "",
    "date": "2025-06-01T22:00:35-0400"
  },
  {
    "title": "AIMPOINT PART #200251 30MM (HIGH) FLIP-TO-SIDE MOUNT W/TWIST MOUNT BASE",
    "url": "https://comblocmarket.com/classifieds1/aimpoint-part-200251-30mm-high-flip-to-side-mount-w-twist-mount-base.6875/",
    "price": "",
    "date": "2025-06-01T18:25:11-0400"
  },
  {
    "title": "WBP Jack 545SR w/Surplus Plum",
    "url": "https://comblocmarket.com/classifieds1/wbp-jack-545sr-w-surplus-plum.6873/",
    "price": "",
    "date": "2025-06-01T17:15:30-0400"
  },
  {
    "title": "Chicom 2-Drum RPD or RPK Gunner's LBE with NOS \"Circle-10\" Drums",
    "url": "https://comblocmarket.com/classifieds1/chicom-2-drum-rpd-or-rpk-gunners-lbe-with-nos-circle-10-drums.5904/",
    "price": "",
    "date": "2025-03-15T13:59:13-0400"
  },
  {
    "title": "Chinese Transitional Magazines (5) with 5-slot Pouch",
    "url": "https://comblocmarket.com/classifieds1/chinese-transitional-magazines-5-with-5-slot-pouch.5872/",
    "price": "",
    "date": "2025-03-12T17:13:39-0400"
  },
  {
    "title": "Russian AK-100 “true black” 30rd mags, Russian & Bulgarian 7n6 ammo",
    "url": "https://comblocmarket.com/classifieds1/russian-ak-100-%E2%80%9Ctrue-black%E2%80%9D-30rd-mags-russian-bulgarian-7n6-ammo.4484/",
    "price": "",
    "date": "2024-10-27T10:43:31-0400"
  },
  {
    "title": "Bergara b14 6.5 cred left hand",
    "url": "https://comblocmarket.com/classifieds1/bergara-b14-6-5-cred-left-hand.6869/",
    "price": "",
    "date": "2025-06-01T13:17:23-0400"
  },
  {
    "title": "Noveske DEVGRU build $1800",
    "url": "https://comblocmarket.com/classifieds1/noveske-devgru-build-1800.6868/",
    "price": "$1800",
    "date": "2025-06-01T13:05:03-0400"
  },
  {
    "title": "Bulgarian ARM9 grip",
    "url": "https://comblocmarket.com/classifieds1/bulgarian-arm9-grip.6815/",
    "price": "",
    "date": "2025-05-29T00:32:01-0400"
  },
  {
    "title": "NIB Arsenal “New Gen” Top Cover",
    "url": "https://comblocmarket.com/classifieds1/nib-arsenal-%E2%80%9Cnew-gen%E2%80%9D-top-cover.6867/",
    "price": "",
    "date": "2025-06-01T12:34:36-0400"
  },
  {
    "title": "Romy Stock, East GERMAN STOCK SET, Witch Dr SAP, Sadu Grip, Russian AK Gas Tubes, Romy Sadu Handguard, B...",
    "url": "https://comblocmarket.com/classifieds1/romy-stock-east-german-stock-set-witch-dr-sap-sadu-grip-russian-ak-gas-tubes-romy-sadu-handguard-bulgy-ak-side-rails-chinese-mags-hk-g3-slings.5227/",
    "price": "",
    "date": "2025-01-16T13:19:22-0500"
  },
  {
    "title": "Russian; KRINKOV BOOSTERS, Trunnions, Bulgy AK Gas Tubes, RPK Slings W/Shoulder Pad, Romy Front Trunnion...",
    "url": "https://comblocmarket.com/classifieds1/russian-krinkov-boosters-trunnions-bulgy-ak-gas-tubes-rpk-slings-w-shoulder-pad-romy-front-trunnions-ak100-fsb-bulgy-side-rail-bake-lowers.5331/",
    "price": "",
    "date": "2025-01-25T13:15:34-0500"
  },
  {
    "title": "Weiger 5.56 Mags, Russian RPK HG’s, ALG ULTIMATE FCG, Arsenal 4.5mm Krink Stock Set, Arsenal Krinkov HG ...",
    "url": "https://comblocmarket.com/classifieds1/weiger-5-56-mags-russian-rpk-hg%E2%80%99s-alg-ultimate-fcg-arsenal-4-5mm-krink-stock-set-arsenal-krinkov-hg-set-draco-rear-trunnion-romy-sadu-lower.4831/",
    "price": "",
    "date": "2024-11-30T13:58:52-0500"
  },
  {
    "title": "Wizzi's parts bin saiga and mag pulls.",
    "url": "https://comblocmarket.com/classifieds1/wizzis-parts-bin-saiga-and-mag-pulls.6866/",
    "price": "",
    "date": "2025-06-01T11:17:40-0400"
  },
  {
    "title": "Molot 5.56 45rd Magazine",
    "url": "https://comblocmarket.com/classifieds1/molot-5-56-45rd-magazine.6865/",
    "price": "",
    "date": "2025-06-01T07:42:17-0400"
  },
  {
    "title": "Arsenal SAS M-7 Premium Storage Box CNC Hard Foam Magnetic Closure Lid",
    "url": "https://comblocmarket.com/classifieds1/arsenal-sas-m-7-premium-storage-box-cnc-hard-foam-magnetic-closure-lid.6864/",
    "price": "",
    "date": "2025-05-31T23:56:24-0400"
  },
  {
    "title": "ARSENAL US POLYMER MILLED HANDGUARD SET W/GRIP",
    "url": "https://comblocmarket.com/classifieds1/arsenal-us-polymer-milled-handguard-set-w-grip.6863/",
    "price": "",
    "date": "2025-05-31T23:54:23-0400"
  },
  {
    "title": "A3 Tactical Modular Folding Stock - 1913 w/modular cheek riser",
    "url": "https://comblocmarket.com/classifieds1/a3-tactical-modular-folding-stock-1913-w-modular-cheek-riser.6858/",
    "price": "",
    "date": "2025-05-31T23:09:41-0400"
  },
  {
    "title": "Near new PWS MK 116 mod 2m in 762x39 for 56s",
    "url": "https://comblocmarket.com/classifieds1/near-new-pws-mk-116-mod-2m-in-762x39-for-56s.5908/",
    "price": "",
    "date": "2025-03-15T19:54:30-0400"
  },
  {
    "title": "Enfield No1Mk3 Grenade Launcher",
    "url": "https://comblocmarket.com/classifieds1/enfield-no1mk3-grenade-launcher.6856/",
    "price": "",
    "date": "2025-05-31T21:31:14-0400"
  },
  {
    "title": "Issued izhmash akm Hgs.",
    "url": "https://comblocmarket.com/classifieds1/issued-izhmash-akm-hgs.6855/",
    "price": "",
    "date": "2025-05-31T21:22:50-0400"
  },
  {
    "title": "Romanian 40s",
    "url": "https://comblocmarket.com/classifieds1/romanian-40s.6822/",
    "price": "",
    "date": "2025-05-29T23:01:45-0400"
  },
  {
    "title": "NIB Genuine Zenitco b-11 Krink Hand guard w/ papers",
    "url": "https://comblocmarket.com/classifieds1/nib-genuine-zenitco-b-11-krink-hand-guard-w-papers.6852/",
    "price": "",
    "date": "2025-05-31T17:26:21-0400"
  },
  {
    "title": "Circle 21/25 firebrick red bulgy mag",
    "url": "https://comblocmarket.com/classifieds1/circle-21-25-firebrick-red-bulgy-mag.6851/",
    "price": "",
    "date": "2025-05-31T16:22:27-0400"
  },
  {
    "title": "Circle 10 Mold 4 Magazines, 5.45x39mm Ammo, Makarov Night Sights, Daewoo Accessories, Bits and Bobs",
    "url": "https://comblocmarket.com/classifieds1/circle-10-mold-4-magazines-5-45x39mm-ammo-makarov-night-sights-daewoo-accessories-bits-and-bobs.6643/",
    "price": "",
    "date": "2025-05-14T12:21:24-0400"
  },
  {
    "title": "Surplus 4.5mm Rear trunnion $100-175",
    "url": "https://comblocmarket.com/classifieds1/surplus-4-5mm-rear-trunnion-100-175.6850/",
    "price": "$100",
    "date": "2025-05-31T15:22:16-0400"
  },
  {
    "title": "wz.96 Beryl & Mini Beryl Pouches with accessories",
    "url": "https://comblocmarket.com/classifieds1/wz-96-beryl-mini-beryl-pouches-with-accessories.6832/",
    "price": "",
    "date": "2025-05-30T13:53:37-0400"
  },
  {
    "title": "Zastava M70 Tiger Maple Rifle. Price Dropped. Arsenal SAM 7R Rare limited edition Rifle.",
    "url": "https://comblocmarket.com/classifieds1/zastava-m70-tiger-maple-rifle-price-dropped-arsenal-sam-7r-rare-limited-edition-rifle.2268/",
    "price": "",
    "date": "2024-02-17T18:57:53-0500"
  },
  {
    "title": "Rare Knives (AK 47 Boker Collection ) Combat  Vests, Drop Leg Holsters!",
    "url": "https://comblocmarket.com/classifieds1/rare-knives-ak-47-boker-collection-combat-vests-drop-leg-holsters.2257/",
    "price": "",
    "date": "2024-02-16T18:46:46-0500"
  },
  {
    "title": "Wtb ... Dshk-38 parts",
    "url": "https://comblocmarket.com/classifieds1/wtb-dshk-38-parts.6849/",
    "price": "",
    "date": "2025-05-31T13:47:40-0400"
  },
  {
    "title": "Parts kits, and Type 63 mags. Update 05/31/25",
    "url": "https://comblocmarket.com/classifieds1/parts-kits-and-type-63-mags-update-05-31-25.6523/",
    "price": "",
    "date": "2025-05-04T18:50:36-0400"
  },
  {
    "title": "[WTB] Surplus Combloc AK mag catch",
    "url": "https://comblocmarket.com/classifieds1/wtb-surplus-combloc-ak-mag-catch.6846/",
    "price": "",
    "date": "2025-05-31T12:14:43-0400"
  },
  {
    "title": "EG Mak Holster, Leather Ducky SAP, Wood HG’S, SVD Cheek Pad, K-USA Muzzle Brake,Romy: 2-Cell AK Pouches,...",
    "url": "https://comblocmarket.com/classifieds1/eg-mak-holster-leather-ducky-sap-wood-hg%E2%80%99s-svd-cheek-pad-k-usa-muzzle-brake-romy-2-cell-ak-pouches-hg-set-w-grip-chinese-lower-polish-ak-stock.5832/",
    "price": "",
    "date": "2025-03-09T13:27:22-0400"
  },
  {
    "title": "Arsenal 4.5MM Krinkov Stock Set, AK-74 Stock, Swedish K SMG Lower, Russian Plum 6x5 Scabbard W/ Frog, 6x...",
    "url": "https://comblocmarket.com/classifieds1/arsenal-4-5mm-krinkov-stock-set-ak-74-stock-swedish-k-smg-lower-russian-plum-6x5-scabbard-w-frog-6x5-bayo-hilt-flecks-romy-ak-hg%E2%80%99s-with-grip.4832/",
    "price": "",
    "date": "2024-11-30T14:06:33-0500"
  },
  {
    "title": "Hungarian 6x3 & Japanese WW2 T30 bayonets",
    "url": "https://comblocmarket.com/classifieds1/hungarian-6x3-japanese-ww2-t30-bayonets.6447/",
    "price": "",
    "date": "2025-04-28T13:32:19-0400"
  },
  {
    "title": "NIB 95-round 5.45x39 KCI drum magazine & blank firing adapters",
    "url": "https://comblocmarket.com/classifieds1/nib-95-round-5-45x39-kci-drum-magazine-blank-firing-adapters.3932/",
    "price": "",
    "date": "2024-08-26T12:40:33-0400"
  },
  {
    "title": "Miscellaneous AK stuff uPdated",
    "url": "https://comblocmarket.com/classifieds1/miscellaneous-ak-stuff-updated.6344/",
    "price": "",
    "date": "2025-04-17T21:03:02-0400"
  },
  {
    "title": "In need of surplus 100 Series parts",
    "url": "https://comblocmarket.com/classifieds1/in-need-of-surplus-100-series-parts.6691/",
    "price": "",
    "date": "2025-05-17T22:48:17-0400"
  },
  {
    "title": "AR heavy barrel with bipod",
    "url": "https://comblocmarket.com/classifieds1/ar-heavy-barrel-with-bipod.6845/",
    "price": "",
    "date": "2025-05-31T09:26:15-0400"
  },
  {
    "title": "CAI Hungarian AK63DS",
    "url": "https://comblocmarket.com/classifieds1/cai-hungarian-ak63ds.6844/",
    "price": "",
    "date": "2025-05-31T09:21:07-0400"
  },
  {
    "title": "duplicate plz delete",
    "url": "https://comblocmarket.com/classifieds1/duplicate-plz-delete.6842/",
    "price": "",
    "date": "2025-05-31T00:38:36-0400"
  },
  {
    "title": "Magpul OD middy furniture & rear sight set",
    "url": "https://comblocmarket.com/classifieds1/magpul-od-middy-furniture-rear-sight-set.6780/",
    "price": "",
    "date": "2025-05-25T20:36:49-0400"
  },
  {
    "title": "(Price drop)Russian red hand guard set.",
    "url": "https://comblocmarket.com/classifieds1/price-drop-russian-red-hand-guard-set.6184/",
    "price": "",
    "date": "2025-04-07T03:34:14-0400"
  },
  {
    "title": "More Added 2/27 AK Parts/Stuff I Need. LINCH DTS & More.",
    "url": "https://comblocmarket.com/classifieds1/more-added-2-27-ak-parts-stuff-i-need-linch-dts-more.1379/",
    "price": "",
    "date": "2023-11-03T21:07:12-0400"
  },
  {
    "title": "More added 3/14 Arsenal,Ultimak Rail, Bipod,Galil, Mini Beryl, AK Stuff, Mech-Tech CCU, Glock parts & NV...",
    "url": "https://comblocmarket.com/classifieds1/more-added-3-14-arsenal-ultimak-rail-bipod-galil-mini-beryl-ak-stuff-mech-tech-ccu-glock-parts-nv-laser.1601/",
    "price": "",
    "date": "2023-11-26T11:33:57-0500"
  },
  {
    "title": "Reproduction East German Wieger STG-940 Furniture Kits",
    "url": "https://comblocmarket.com/classifieds1/reproduction-east-german-wieger-stg-940-furniture-kits.5190/",
    "price": "",
    "date": "2025-01-12T11:59:51-0500"
  },
  {
    "title": "Ak100 Square Lug 90° Gas Block",
    "url": "https://comblocmarket.com/classifieds1/ak100-square-lug-90%C2%B0-gas-block.5863/",
    "price": "",
    "date": "2025-03-11T19:26:41-0400"
  },
  {
    "title": "Pile of Chinese Mags and a couple Weigers",
    "url": "https://comblocmarket.com/classifieds1/pile-of-chinese-mags-and-a-couple-weigers.6170/",
    "price": "",
    "date": "2025-04-06T16:46:35-0400"
  },
  {
    "title": "[WTB] Strela Flash Hider 14x1LH",
    "url": "https://comblocmarket.com/classifieds1/wtb-strela-flash-hider-14x1lh.6840/",
    "price": "",
    "date": "2025-05-30T17:42:13-0400"
  },
  {
    "title": "[WTB] STRELA Flash Hider 14x1LH",
    "url": "https://comblocmarket.com/classifieds1/wtb-strela-flash-hider-14x1lh.6839/",
    "price": "",
    "date": "2025-05-30T17:41:42-0400"
  },
  {
    "title": "Zenitco pt-1 wide pad",
    "url": "https://comblocmarket.com/classifieds1/zenitco-pt-1-wide-pad.6838/",
    "price": "",
    "date": "2025-05-30T16:25:03-0400"
  },
  {
    "title": "WTS: Molot Vepr 12 Gauge Black Polymer 8 Round Magazine",
    "url": "https://comblocmarket.com/classifieds1/wts-molot-vepr-12-gauge-black-polymer-8-round-magazine.6837/",
    "price": "",
    "date": "2025-05-30T16:21:07-0400"
  },
  {
    "title": "STOP Marring Your Sling Loop/Handguard retainer! U-Loop Blue Force Gear Vickers Sling Coyote Brown Perfe...",
    "url": "https://comblocmarket.com/classifieds1/stop-marring-your-sling-loop-handguard-retainer-u-loop-blue-force-gear-vickers-sling-coyote-brown-perfect-for-aks.6836/",
    "price": "",
    "date": "2025-05-30T15:58:16-0400"
  },
  {
    "title": "Price Check: Norinco Mak-90 Sporter",
    "url": "https://comblocmarket.com/classifieds1/price-check-norinco-mak-90-sporter.6834/",
    "price": "",
    "date": "2025-05-30T15:03:24-0400"
  },
  {
    "title": "Chinese 30 round Polytech, stainless steel followers, and 3 witness holes 1# is the last one.",
    "url": "https://comblocmarket.com/classifieds1/chinese-30-round-polytech-stainless-steel-followers-and-3-witness-holes-1-is-the-last-one.6833/",
    "price": "",
    "date": "2025-05-30T14:04:20-0400"
  },
  {
    "title": "Izzy Longtop for sale",
    "url": "https://comblocmarket.com/classifieds1/izzy-longtop-for-sale.6830/",
    "price": "",
    "date": "2025-05-30T13:46:07-0400"
  },
  {
    "title": "AES-10B",
    "url": "https://comblocmarket.com/classifieds1/aes-10b.6828/",
    "price": "",
    "date": "2025-05-30T11:23:41-0400"
  },
  {
    "title": "WTB Shotgun With 26\"+ Barrel",
    "url": "https://comblocmarket.com/classifieds1/wtb-shotgun-with-26-barrel.6807/",
    "price": "",
    "date": "2025-05-28T01:46:44-0400"
  },
  {
    "title": "Romy G Stock Set PRICE DROP",
    "url": "https://comblocmarket.com/classifieds1/romy-g-stock-set-price-drop.6702/",
    "price": "",
    "date": "2025-05-19T12:18:38-0400"
  },
  {
    "title": "Norinco Dust Cover Scope Rail Vintage",
    "url": "https://comblocmarket.com/classifieds1/norinco-dust-cover-scope-rail-vintage.6827/",
    "price": "",
    "date": "2025-05-30T09:42:49-0400"
  },
  {
    "title": "Norinco 84S 5.56 NATO Mags",
    "url": "https://comblocmarket.com/classifieds1/norinco-84s-5-56-nato-mags.6826/",
    "price": "",
    "date": "2025-05-30T09:36:01-0400"
  },
  {
    "title": "M16 Bake grips",
    "url": "https://comblocmarket.com/classifieds1/m16-bake-grips.6675/",
    "price": "",
    "date": "2025-05-16T16:32:46-0400"
  },
  {
    "title": "Ak patches , iron ons and more.",
    "url": "https://comblocmarket.com/classifieds1/ak-patches-iron-ons-and-more.6428/",
    "price": "",
    "date": "2025-04-26T11:54:38-0400"
  },
  {
    "title": "4pcs of Plum Izhmash 5.45 Mags/ 1pcs - $65",
    "url": "https://comblocmarket.com/classifieds1/4pcs-of-plum-izhmash-5-45-mags-1pcs-65.6604/",
    "price": "$65",
    "date": "2025-05-11T11:41:18-0400"
  },
  {
    "title": "Price drop WBP 5.56 parts kit",
    "url": "https://comblocmarket.com/classifieds1/price-drop-wbp-5-56-parts-kit.5406/",
    "price": "",
    "date": "2025-01-30T21:07:12-0500"
  },
  {
    "title": "AKM magpul stock",
    "url": "https://comblocmarket.com/classifieds1/akm-magpul-stock.6512/",
    "price": "",
    "date": "2025-05-03T20:46:39-0400"
  },
  {
    "title": "PSA AKM handguard set",
    "url": "https://comblocmarket.com/classifieds1/psa-akm-handguard-set.5693/",
    "price": "",
    "date": "2025-02-25T13:51:38-0500"
  },
  {
    "title": "PP-19 Vityaz Magazine Pouch wanted",
    "url": "https://comblocmarket.com/classifieds1/pp-19-vityaz-magazine-pouch-wanted.3416/",
    "price": "",
    "date": "2024-06-25T13:25:51-0400"
  },
  {
    "title": "Plum upper handguard,Bulgarian salmon grip or Bulgarian black grip",
    "url": "https://comblocmarket.com/classifieds1/plum-upper-handguard-bulgarian-salmon-grip-or-bulgarian-black-grip.6824/",
    "price": "",
    "date": "2025-05-30T01:24:49-0400"
  },
  {
    "title": "BULGARIAN ARSENAL 4 PIECE FLASH HIDERS",
    "url": "https://comblocmarket.com/classifieds1/bulgarian-arsenal-4-piece-flash-hiders.6823/",
    "price": "",
    "date": "2025-05-29T23:27:50-0400"
  },
  {
    "title": "Krinkov Quad Rail",
    "url": "https://comblocmarket.com/classifieds1/krinkov-quad-rail.6712/",
    "price": "",
    "date": "2025-05-20T20:58:02-0400"
  },
  {
    "title": "Zpap m70 cash or trade",
    "url": "https://comblocmarket.com/classifieds1/zpap-m70-cash-or-trade.6756/",
    "price": "",
    "date": "2025-05-23T23:06:03-0400"
  },
  {
    "title": "M70ab2 underfolder",
    "url": "https://comblocmarket.com/classifieds1/m70ab2-underfolder.6761/",
    "price": "",
    "date": "2025-05-24T13:01:05-0400"
  },
  {
    "title": "Yugo Grenade gas block/fsb nightsight for your ZPAP GB/FSB",
    "url": "https://comblocmarket.com/classifieds1/yugo-grenade-gas-block-fsb-nightsight-for-your-zpap-gb-fsb.6819/",
    "price": "",
    "date": "2025-05-29T19:50:13-0400"
  },
  {
    "title": "RS Regulate Rail and CNC Warrior Flash Hider",
    "url": "https://comblocmarket.com/classifieds1/rs-regulate-rail-and-cnc-warrior-flash-hider.6762/",
    "price": "",
    "date": "2025-05-24T13:22:57-0400"
  },
  {
    "title": "Late 80s Polish Parts Kit SPF",
    "url": "https://comblocmarket.com/classifieds1/late-80s-polish-parts-kit-spf.6818/",
    "price": "",
    "date": "2025-05-29T19:08:15-0400"
  },
  {
    "title": "Steel reinforced Arsenial/Bulgaria Smoke waffle 20 & 30 round magazines in 223/556.",
    "url": "https://comblocmarket.com/classifieds1/steel-reinforced-arsenial-bulgaria-smoke-waffle-20-30-round-magazines-in-223-556.6609/",
    "price": "",
    "date": "2025-05-11T18:19:35-0400"
  },
  {
    "title": "Polytech FSB",
    "url": "https://comblocmarket.com/classifieds1/polytech-fsb.5869/",
    "price": "",
    "date": "2025-03-12T15:20:05-0400"
  },
  {
    "title": "3 Molot 45 rd Bakelite magazine 5.45x39",
    "url": "https://comblocmarket.com/classifieds1/3-molot-45-rd-bakelite-magazine-5-45x39.6567/",
    "price": "",
    "date": "2025-05-08T11:51:47-0400"
  },
  {
    "title": "SSO Russian Gear - Old gen Smersh rig, Sumrak suit",
    "url": "https://comblocmarket.com/classifieds1/sso-russian-gear-old-gen-smersh-rig-sumrak-suit.6790/",
    "price": "",
    "date": "2025-05-26T14:02:11-0400"
  },
  {
    "title": "[WTS][IL] 40rnd Molot Bakelite Mags",
    "url": "https://comblocmarket.com/classifieds1/wts-il-40rnd-molot-bakelite-mags.6749/",
    "price": "",
    "date": "2025-05-23T18:23:19-0400"
  },
  {
    "title": "Circle 10 Customs Fixed Triangle Stock",
    "url": "https://comblocmarket.com/classifieds1/circle-10-customs-fixed-triangle-stock.6816/",
    "price": "",
    "date": "2025-05-29T00:40:31-0400"
  },
  {
    "title": "NIB Arsenal Krink 7.62 Barrel Assembly KR-136B",
    "url": "https://comblocmarket.com/classifieds1/nib-arsenal-krink-7-62-barrel-assembly-kr-136b.6814/",
    "price": "",
    "date": "2025-05-29T00:21:24-0400"
  },
  {
    "title": "(3)Hungarian 20 rd. tanker mags standard w hungarian 3 cell pouch w hungarian leather sling",
    "url": "https://comblocmarket.com/classifieds1/3-hungarian-20-rd-tanker-mags-standard-w-hungarian-3-cell-pouch-w-hungarian-leather-sling.6778/",
    "price": "",
    "date": "2025-05-25T18:07:18-0400"
  },
  {
    "title": "Polytech Spiker AKS-762 Free Ship",
    "url": "https://comblocmarket.com/classifieds1/polytech-spiker-aks-762-free-ship.6474/",
    "price": "",
    "date": "2025-04-30T19:34:48-0400"
  },
  {
    "title": "Davranov Chest Rig *NEW*",
    "url": "https://comblocmarket.com/classifieds1/davranov-chest-rig-new.6721/",
    "price": "",
    "date": "2025-05-21T19:11:19-0400"
  },
  {
    "title": "Arsenal 2-stage Vepr/Saiga 12 FCG",
    "url": "https://comblocmarket.com/classifieds1/arsenal-2-stage-vepr-saiga-12-fcg.6599/",
    "price": "",
    "date": "2025-05-11T00:14:58-0400"
  },
  {
    "title": "Bulgarian AK74 Trunnion, Bolt, and Carrier",
    "url": "https://comblocmarket.com/classifieds1/bulgarian-ak74-trunnion-bolt-and-carrier.6813/",
    "price": "",
    "date": "2025-05-28T21:17:49-0400"
  },
  {
    "title": "Chinese Norinco 56S / Mak90/ Polytech chu wood buttstocks - blems",
    "url": "https://comblocmarket.com/classifieds1/chinese-norinco-56s-mak90-polytech-chu-wood-buttstocks-blems.6792/",
    "price": "",
    "date": "2025-05-26T15:02:30-0400"
  },
  {
    "title": "Molotov Mfg. Yugo M70 hg",
    "url": "https://comblocmarket.com/classifieds1/molotov-mfg-yugo-m70-hg.5436/",
    "price": "",
    "date": "2025-02-02T13:22:47-0500"
  },
  {
    "title": "RS Regulate AK-312M + AKOT Combo",
    "url": "https://comblocmarket.com/classifieds1/rs-regulate-ak-312m-akot-combo.6620/",
    "price": "",
    "date": "2025-05-12T16:38:47-0400"
  },
  {
    "title": "Beryl handguard set",
    "url": "https://comblocmarket.com/classifieds1/beryl-handguard-set.5630/",
    "price": "",
    "date": "2025-02-17T15:27:43-0500"
  },
  {
    "title": "Looking for your beat to hell and back 10/22.",
    "url": "https://comblocmarket.com/classifieds1/looking-for-your-beat-to-hell-and-back-10-22.6812/",
    "price": "",
    "date": "2025-05-28T16:35:06-0400"
  },
  {
    "title": "Polytech Poly Technologies Inc., 5.56mm Bore Collimator w/Original Box & Manual",
    "url": "https://comblocmarket.com/classifieds1/polytech-poly-technologies-inc-5-56mm-bore-collimator-w-original-box-manual.5873/",
    "price": "",
    "date": "2025-03-12T17:17:21-0400"
  },
  {
    "title": "Soviet/Russian Berezhka Camo Coverall w/Hood & Mask - Extra-Large/Tall",
    "url": "https://comblocmarket.com/classifieds1/soviet-russian-berezhka-camo-coverall-w-hood-mask-extra-large-tall.5903/",
    "price": "",
    "date": "2025-03-15T13:54:03-0400"
  },
  {
    "title": "Cnc w. 14x1 lh  ak muzzle brake new/slr synergy 14x1 lh brake new.BOTH come together bundled",
    "url": "https://comblocmarket.com/classifieds1/cnc-w-14x1-lh-ak-muzzle-brake-new-slr-synergy-14x1-lh-brake-new-both-come-together-bundled.6811/",
    "price": "",
    "date": "2025-05-28T15:58:21-0400"
  },
  {
    "title": "Molotov MFG MK62 Lower HG (Zenitclone), Strela Sputnik Gen 2, 2007 Bushnell Holosight",
    "url": "https://comblocmarket.com/classifieds1/molotov-mfg-mk62-lower-hg-zenitclone-strela-sputnik-gen-2-2007-bushnell-holosight.6809/",
    "price": "",
    "date": "2025-05-28T15:27:43-0400"
  },
  {
    "title": "BULGARIAN ARSENAL AMBI SAFETY SELECTORS",
    "url": "https://comblocmarket.com/classifieds1/bulgarian-arsenal-ambi-safety-selectors.6522/",
    "price": "",
    "date": "2025-05-04T18:05:53-0400"
  },
  {
    "title": "Sureshot mk2.1, Midwest alpha stock, Jmac MKRT trunnion with pic attachment",
    "url": "https://comblocmarket.com/classifieds1/sureshot-mk2-1-midwest-alpha-stock-jmac-mkrt-trunnion-with-pic-attachment.6592/",
    "price": "",
    "date": "2025-05-10T18:20:00-0400"
  },
  {
    "title": "Molot Vepr 74",
    "url": "https://comblocmarket.com/classifieds1/molot-vepr-74.4312/",
    "price": "",
    "date": "2024-10-08T18:53:46-0400"
  },
  {
    "title": "Price drop - Ukrainian and Russian uniforms, truspec and propper multicam trousers",
    "url": "https://comblocmarket.com/classifieds1/price-drop-ukrainian-and-russian-uniforms-truspec-and-propper-multicam-trousers.5422/",
    "price": "",
    "date": "2025-02-01T01:55:27-0500"
  },
  {
    "title": "Norinco 56S Sile blue bolt",
    "url": "https://comblocmarket.com/classifieds1/norinco-56s-sile-blue-bolt.6531/",
    "price": "",
    "date": "2025-05-05T16:40:21-0400"
  },
  {
    "title": "SAR-3 Mags",
    "url": "https://comblocmarket.com/classifieds1/sar-3-mags.6806/",
    "price": "",
    "date": "2025-05-27T21:50:56-0400"
  },
  {
    "title": "RS Regulate/Aimpoint PRO AKM Setup, JLD PTR91 Steel Lower Complete",
    "url": "https://comblocmarket.com/classifieds1/rs-regulate-aimpoint-pro-akm-setup-jld-ptr91-steel-lower-complete.6805/",
    "price": "",
    "date": "2025-05-27T19:30:35-0400"
  },
  {
    "title": "Polish 80% 5.56/5.45 Receiver Blanks",
    "url": "https://comblocmarket.com/classifieds1/polish-80-5-56-5-45-receiver-blanks.6804/",
    "price": "",
    "date": "2025-05-27T17:56:17-0400"
  },
  {
    "title": "AK12 Barrels Chambered in 7.62x39, US-Made, Obstreperous, non-CHF, Chrome Lined, 23mm (Each)",
    "url": "https://comblocmarket.com/classifieds1/ak12-barrels-chambered-in-7-62x39-us-made-obstreperous-non-chf-chrome-lined-23mm-each.6686/",
    "price": "",
    "date": "2025-05-17T17:33:58-0400"
  },
  {
    "title": "Chrome follower Chinese and Izzy flatback bake",
    "url": "https://comblocmarket.com/classifieds1/chrome-follower-chinese-and-izzy-flatback-bake.6803/",
    "price": "",
    "date": "2025-05-27T17:20:54-0400"
  },
  {
    "title": "5.45x39 steel mags value?",
    "url": "https://comblocmarket.com/classifieds1/5-45x39-steel-mags-value.6801/",
    "price": "",
    "date": "2025-05-27T15:56:47-0400"
  },
  {
    "title": "Part Bin Clean Out",
    "url": "https://comblocmarket.com/classifieds1/part-bin-clean-out.6799/",
    "price": "",
    "date": "2025-05-27T11:48:55-0400"
  },
  {
    "title": "Preban Norinco 120rd AR15 / M16 Drum",
    "url": "https://comblocmarket.com/classifieds1/preban-norinco-120rd-ar15-m16-drum.6222/",
    "price": "",
    "date": "2025-04-09T10:26:01-0400"
  },
  {
    "title": "PreBan Norinco Bipod Quick Detach",
    "url": "https://comblocmarket.com/classifieds1/preban-norinco-bipod-quick-detach.6333/",
    "price": "",
    "date": "2025-04-17T10:44:54-0400"
  },
  {
    "title": "WTB Polish Tantal bolt Carrier",
    "url": "https://comblocmarket.com/classifieds1/wtb-polish-tantal-bolt-carrier.6408/",
    "price": "",
    "date": "2025-04-24T13:41:58-0400"
  },
  {
    "title": "SOLD Bulgarian Bakelite Goodies SOLD",
    "url": "https://comblocmarket.com/classifieds1/sold-bulgarian-bakelite-goodies-sold.5588/",
    "price": "",
    "date": "2025-02-14T13:40:23-0500"
  },
  {
    "title": "Eotech XPS3-0, Zenitco B10M",
    "url": "https://comblocmarket.com/classifieds1/eotech-xps3-0-zenitco-b10m.6738/",
    "price": "",
    "date": "2025-05-23T00:00:55-0400"
  },
  {
    "title": "SKS Yugo 59/66 bayonet",
    "url": "https://comblocmarket.com/classifieds1/sks-yugo-59-66-bayonet.6798/",
    "price": "",
    "date": "2025-05-26T21:34:30-0400"
  },
  {
    "title": "Cetme / HK magazines",
    "url": "https://comblocmarket.com/classifieds1/cetme-hk-magazines.6797/",
    "price": "",
    "date": "2025-05-26T21:28:12-0400"
  },
  {
    "title": "Arisaka type 99 barreled action.",
    "url": "https://comblocmarket.com/classifieds1/arisaka-type-99-barreled-action.6796/",
    "price": "",
    "date": "2025-05-26T21:20:53-0400"
  },
  {
    "title": "1984 Original Barrel Romy G",
    "url": "https://comblocmarket.com/classifieds1/1984-original-barrel-romy-g.6795/",
    "price": "",
    "date": "2025-05-26T21:04:14-0400"
  },
  {
    "title": "Bulgarian Hand Guards",
    "url": "https://comblocmarket.com/classifieds1/bulgarian-hand-guards.6722/",
    "price": "",
    "date": "2025-05-21T20:40:02-0400"
  },
  {
    "title": "RPK rear sight (PRICE DROP)",
    "url": "https://comblocmarket.com/classifieds1/rpk-rear-sight-price-drop.6636/",
    "price": "",
    "date": "2025-05-13T21:19:39-0400"
  },
  {
    "title": "Molot ribbed true black 45 round",
    "url": "https://comblocmarket.com/classifieds1/molot-ribbed-true-black-45-round.6793/",
    "price": "",
    "date": "2025-05-26T15:05:04-0400"
  },
  {
    "title": "Original USGI m16a1 handguards",
    "url": "https://comblocmarket.com/classifieds1/original-usgi-m16a1-handguards.6760/",
    "price": "",
    "date": "2025-05-24T11:48:52-0400"
  },
  {
    "title": "Russian ak74 stock set, Polish akm stock set, Romanian Palmswell trenchart set, New Romanian dust cover,...",
    "url": "https://comblocmarket.com/classifieds1/russian-ak74-stock-set-polish-akm-stock-set-romanian-palmswell-trenchart-set-new-romanian-dust-cover-cheese-grater-arsenal-sling-us-ak100-muzzle.6789/",
    "price": "",
    "date": "2025-05-26T13:55:04-0400"
  },
  {
    "title": "Found",
    "url": "https://comblocmarket.com/classifieds1/found.6787/",
    "price": "",
    "date": "2025-05-26T12:49:50-0400"
  },
  {
    "title": "Pulled Bulgarian Type 3 barrels",
    "url": "https://comblocmarket.com/classifieds1/pulled-bulgarian-type-3-barrels.6763/",
    "price": "",
    "date": "2025-05-24T13:54:47-0400"
  },
  {
    "title": "Bulgy Milled Kit \"Denis\"",
    "url": "https://comblocmarket.com/classifieds1/bulgy-milled-kit-denis.6557/",
    "price": "",
    "date": "2025-05-07T20:42:11-0400"
  },
  {
    "title": "Beretta 84BB trade for older revolvers / other older guns",
    "url": "https://comblocmarket.com/classifieds1/beretta-84bb-trade-for-older-revolvers-other-older-guns.6706/",
    "price": "",
    "date": "2025-05-20T08:30:02-0400"
  },
  {
    "title": "G3 Bolt Head, Enfield Contract NOS",
    "url": "https://comblocmarket.com/classifieds1/g3-bolt-head-enfield-contract-nos.6786/",
    "price": "",
    "date": "2025-05-26T08:57:36-0400"
  },
  {
    "title": "Looking to buy a VZ61 parts kit",
    "url": "https://comblocmarket.com/classifieds1/looking-to-buy-a-vz61-parts-kit.6785/",
    "price": "",
    "date": "2025-05-26T03:09:17-0400"
  },
  {
    "title": "AK74M AK100 AK74 lower handguard retainer",
    "url": "https://comblocmarket.com/classifieds1/ak74m-ak100-ak74-lower-handguard-retainer.5532/",
    "price": "",
    "date": "2025-02-09T20:10:48-0500"
  },
  {
    "title": "(Price Drop) OG Russian Soviet AKM 4 piece stock set",
    "url": "https://comblocmarket.com/classifieds1/price-drop-og-russian-soviet-akm-4-piece-stock-set.6493/",
    "price": "",
    "date": "2025-05-02T09:25:06-0400"
  },
  {
    "title": "Circle 10 74 kit",
    "url": "https://comblocmarket.com/classifieds1/circle-10-74-kit.6782/",
    "price": "",
    "date": "2025-05-25T20:59:08-0400"
  },
  {
    "title": "East German Wire Folding Stock & East German AK74 Safety Selector",
    "url": "https://comblocmarket.com/classifieds1/east-german-wire-folding-stock-east-german-ak74-safety-selector.6781/",
    "price": "",
    "date": "2025-05-25T20:51:56-0400"
  },
  {
    "title": "Yugo rear night sight, Cloud Defensive Rein, TDI Arms MLOK M70 HG, Epsilon VG6 and more",
    "url": "https://comblocmarket.com/classifieds1/yugo-rear-night-sight-cloud-defensive-rein-tdi-arms-mlok-m70-hg-epsilon-vg6-and-more.6143/",
    "price": "",
    "date": "2025-04-04T17:47:21-0400"
  },
  {
    "title": "Early Soviet SKS Bayonet w/ Straight-Cut Collar, Saiga Gas Tubes, RPD Tool/Accessory Kit",
    "url": "https://comblocmarket.com/classifieds1/early-soviet-sks-bayonet-w-straight-cut-collar-saiga-gas-tubes-rpd-tool-accessory-kit.6779/",
    "price": "",
    "date": "2025-05-25T18:32:40-0400"
  },
  {
    "title": "Chinese Norinco 56S / Mak90/ Polytech chu wood buttstocks + blems",
    "url": "https://comblocmarket.com/classifieds1/chinese-norinco-56s-mak90-polytech-chu-wood-buttstocks-blems.6406/",
    "price": "",
    "date": "2025-04-24T07:54:00-0400"
  },
  {
    "title": "Some kind of Chinese carrying case",
    "url": "https://comblocmarket.com/classifieds1/some-kind-of-chinese-carrying-case.6777/",
    "price": "",
    "date": "2025-05-25T17:55:46-0400"
  },
  {
    "title": "Polish military bfpu laminate stock..polish bag .polish nos upper handgaurd n (free )wbp enhanced safety...",
    "url": "https://comblocmarket.com/classifieds1/polish-military-bfpu-laminate-stock-polish-bag-polish-nos-upper-handgaurd-n-free-wbp-enhanced-safety-lever.6776/",
    "price": "",
    "date": "2025-05-25T16:58:42-0400"
  },
  {
    "title": "TULA BAKELITE",
    "url": "https://comblocmarket.com/classifieds1/tula-bakelite.6775/",
    "price": "",
    "date": "2025-05-25T13:46:47-0400"
  },
  {
    "title": "Unfired 551A1 in original box w/ accessories trade",
    "url": "https://comblocmarket.com/classifieds1/unfired-551a1-in-original-box-w-accessories-trade.5567/",
    "price": "",
    "date": "2025-02-12T20:05:14-0500"
  },
  {
    "title": "Uncommon AK Mags for sale",
    "url": "https://comblocmarket.com/classifieds1/uncommon-ak-mags-for-sale.6773/",
    "price": "",
    "date": "2025-05-24T22:38:17-0400"
  },
  {
    "title": "RUSSIAN AKM CLEANING KIT (NOS)",
    "url": "https://comblocmarket.com/classifieds1/russian-akm-cleaning-kit-nos.6772/",
    "price": "",
    "date": "2025-05-24T19:29:38-0400"
  },
  {
    "title": "ROMANIAN PSL LEATHER SLING (NOS)",
    "url": "https://comblocmarket.com/classifieds1/romanian-psl-leather-sling-nos.6771/",
    "price": "",
    "date": "2025-05-24T19:27:34-0400"
  },
  {
    "title": "GLOCK 35 GEN 3 OEM BARREL (LOW ROUND COUNT)",
    "url": "https://comblocmarket.com/classifieds1/glock-35-gen-3-oem-barrel-low-round-count.6770/",
    "price": "",
    "date": "2025-05-24T19:25:31-0400"
  },
  {
    "title": "AK12 Magazine sold",
    "url": "https://comblocmarket.com/classifieds1/ak12-magazine-sold.6623/",
    "price": "",
    "date": "2025-05-12T18:41:38-0400"
  },
  {
    "title": "Folding stock for wz.96 Beryl / Mini Beryl",
    "url": "https://comblocmarket.com/classifieds1/folding-stock-for-wz-96-beryl-mini-beryl.6769/",
    "price": "",
    "date": "2025-05-24T17:41:01-0400"
  },
  {
    "title": "Bosnian 2 rib/bosnian gibbs matra 762x39 plus free yugo grip",
    "url": "https://comblocmarket.com/classifieds1/bosnian-2-rib-bosnian-gibbs-matra-762x39-plus-free-yugo-grip.6768/",
    "price": "",
    "date": "2025-05-24T17:07:26-0400"
  },
  {
    "title": "Battle arms Ak ekg trigger",
    "url": "https://comblocmarket.com/classifieds1/battle-arms-ak-ekg-trigger.6413/",
    "price": "",
    "date": "2025-04-25T10:28:16-0400"
  },
  {
    "title": "Vortex Strike Eagle",
    "url": "https://comblocmarket.com/classifieds1/vortex-strike-eagle.6766/",
    "price": "",
    "date": "2025-05-24T15:28:24-0400"
  },
  {
    "title": "Colt / FN  rifle buffer tube & glossy A2 grip",
    "url": "https://comblocmarket.com/classifieds1/colt-fn-rifle-buffer-tube-glossy-a2-grip.6764/",
    "price": "",
    "date": "2025-05-24T14:08:20-0400"
  },
  {
    "title": "Ak 103",
    "url": "https://comblocmarket.com/classifieds1/ak-103.5626/",
    "price": "",
    "date": "2025-02-17T11:10:18-0500"
  },
  {
    "title": "SKS Fixed Mags",
    "url": "https://comblocmarket.com/classifieds1/sks-fixed-mags.6758/",
    "price": "",
    "date": "2025-05-24T09:42:30-0400"
  },
  {
    "title": "Authentic Izhmash AK-100 parts for an authentic AK-103 clone!",
    "url": "https://comblocmarket.com/classifieds1/authentic-izhmash-ak-100-parts-for-an-authentic-ak-103-clone.6361/",
    "price": "",
    "date": "2025-04-18T22:10:30-0400"
  },
  {
    "title": "WTB BFPU Russian Ak74 wood handguards.",
    "url": "https://comblocmarket.com/classifieds1/wtb-bfpu-russian-ak74-wood-handguards.6757/",
    "price": "",
    "date": "2025-05-24T04:48:58-0400"
  },
  {
    "title": "(Price drop)Russian 7.62 Bakelite mags Tula Cyrillic / Izzy",
    "url": "https://comblocmarket.com/classifieds1/price-drop-russian-7-62-bakelite-mags-tula-cyrillic-izzy.6183/",
    "price": "",
    "date": "2025-04-07T02:52:40-0400"
  },
  {
    "title": "Bosnian 2 rib /and bosnian gibbs /matra 762x39 mags",
    "url": "https://comblocmarket.com/classifieds1/bosnian-2-rib-and-bosnian-gibbs-matra-762x39-mags.6753/",
    "price": "",
    "date": "2025-05-23T21:00:07-0400"
  },
  {
    "title": "Molot Vepr FM74-21 5.45x39mm",
    "url": "https://comblocmarket.com/classifieds1/molot-vepr-fm74-21-5-45x39mm.6692/",
    "price": "",
    "date": "2025-05-18T15:31:04-0400"
  },
  {
    "title": "TULA 7.62 BAKELITE MAG BFPU",
    "url": "https://comblocmarket.com/classifieds1/tula-7-62-bakelite-mag-bfpu.6746/",
    "price": "",
    "date": "2025-05-23T18:13:51-0400"
  },
  {
    "title": "IZHMASH WAFFLE ALUMINUM MAG",
    "url": "https://comblocmarket.com/classifieds1/izhmash-waffle-aluminum-mag.6745/",
    "price": "",
    "date": "2025-05-23T18:10:46-0400"
  },
  {
    "title": "Soviet SSH-60 Steel Helmet",
    "url": "https://comblocmarket.com/classifieds1/soviet-ssh-60-steel-helmet.5286/",
    "price": "",
    "date": "2025-01-20T14:24:08-0500"
  }
]
